SklearnYuTensorflowJiqiXuexiShiyongZhinanDierBan/README.md
SklearnYuTensorflowJiqiXuexiShiyongZhinanDierBan/__init__.py
SklearnYuTensorflowJiqiXuexiShiyongZhinanDierBan/__main__.py
SklearnYuTensorflowJiqiXuexiShiyongZhinanDierBan/file.epub
SklearnYuTensorflowJiqiXuexiShiyongZhinanDierBan/index.html
SklearnYuTensorflowJiqiXuexiShiyongZhinanDierBan/css/__init__.py
SklearnYuTensorflowJiqiXuexiShiyongZhinanDierBan/css/annotations.css
SklearnYuTensorflowJiqiXuexiShiyongZhinanDierBan/css/main.css
SklearnYuTensorflowJiqiXuexiShiyongZhinanDierBan/css/normalize.css
SklearnYuTensorflowJiqiXuexiShiyongZhinanDierBan/css/popup.css
SklearnYuTensorflowJiqiXuexiShiyongZhinanDierBan/font/__init__.py
SklearnYuTensorflowJiqiXuexiShiyongZhinanDierBan/font/fontello.eot
SklearnYuTensorflowJiqiXuexiShiyongZhinanDierBan/font/fontello.svg
SklearnYuTensorflowJiqiXuexiShiyongZhinanDierBan/font/fontello.ttf
SklearnYuTensorflowJiqiXuexiShiyongZhinanDierBan/font/fontello.woff
SklearnYuTensorflowJiqiXuexiShiyongZhinanDierBan/img/__init__.py
SklearnYuTensorflowJiqiXuexiShiyongZhinanDierBan/img/annotator-glyph-sprite.png
SklearnYuTensorflowJiqiXuexiShiyongZhinanDierBan/img/annotator-icon-sprite.png
SklearnYuTensorflowJiqiXuexiShiyongZhinanDierBan/img/apple-touch-icon.png
SklearnYuTensorflowJiqiXuexiShiyongZhinanDierBan/img/cancelfullscreen.png
SklearnYuTensorflowJiqiXuexiShiyongZhinanDierBan/img/close.png
SklearnYuTensorflowJiqiXuexiShiyongZhinanDierBan/img/fullscreen.png
SklearnYuTensorflowJiqiXuexiShiyongZhinanDierBan/img/loader.gif
SklearnYuTensorflowJiqiXuexiShiyongZhinanDierBan/img/menu-icon.png
SklearnYuTensorflowJiqiXuexiShiyongZhinanDierBan/img/save.png
SklearnYuTensorflowJiqiXuexiShiyongZhinanDierBan/img/saved.png
SklearnYuTensorflowJiqiXuexiShiyongZhinanDierBan/img/settings-s.png
SklearnYuTensorflowJiqiXuexiShiyongZhinanDierBan/img/settings.png
SklearnYuTensorflowJiqiXuexiShiyongZhinanDierBan/img/star.png
SklearnYuTensorflowJiqiXuexiShiyongZhinanDierBan/js/__init__.py
sklearn_yu_tensorflow_jiqi_xuexi_shiyong_zhinan_dier_ban-2024.3.5.0.dist-info/METADATA
sklearn_yu_tensorflow_jiqi_xuexi_shiyong_zhinan_dier_ban-2024.3.5.0.dist-info/WHEEL
sklearn_yu_tensorflow_jiqi_xuexi_shiyong_zhinan_dier_ban-2024.3.5.0.dist-info/entry_points.txt
sklearn_yu_tensorflow_jiqi_xuexi_shiyong_zhinan_dier_ban-2024.3.5.0.dist-info/top_level.txt
sklearn_yu_tensorflow_jiqi_xuexi_shiyong_zhinan_dier_ban-2024.3.5.0.dist-info/RECORD
